{"ch-any_hide-unsafe-casts.md":"DRNvBVRi","ch-any_narrowest-any.md":"DX4d2sA2","ch-any_never-unknown.md":"DyFy7aES","ch-any_specific-any.md":"Do382P78","ch-any_type-percentage.md":"DUNLHJ2U","ch-any_type-safe-monkey.md":"BeAc5l_y","ch-any_unsoundness.md":"j9fvJN3b","ch-declarations_augment-improve.md":"CTR-eMmX","ch-declarations_dev-dependencies.md":"lr2SZcTS","ch-declarations_export-your-types.md":"2_CpRRJ4","ch-declarations_mirror-types-for-deps.md":"D2-BKe_d","ch-declarations_this-in-callbacks.md":"DbiMzWjW","ch-declarations_three-versions.md":"B0aSZN6a","ch-declarations_use-tsdoc.md":"beH68CSr","ch-design_avoid-optional.md":"C4t656CK","ch-design_avoid-strings.md":"D8JaWrbH","ch-design_consider-codegen.md":"DvC9oiL4","ch-design_in-domain-null.md":"DvhlwxT6","ch-design_incomplete-over-inaccurate.md":"ZrBAgoTF","ch-design_jsdoc-repeat.md":"DVnp5NAt","ch-design_language-of-domain.md":"BQQPa_Kt","ch-design_loose-accept-strict-produce.md":"B4WC5bzl","ch-design_null-in-type.md":"WzJN11UN","ch-design_null-values-to-perimeter.md":"DTWTku_F","ch-design_same-type-params.md":"DSU5Xb-p","ch-design_unify.md":"CIoBFEke","ch-design_union-of-interfaces.md":"DgOd-7p3","ch-design_valid-states.md":"C3FyLII-","ch-generics_codegen-alt.md":"B4_dBChE","ch-generics_conditional-overload.md":"CmRoZ6gd","ch-generics_control-distribution.md":"COvnm6Tu","ch-generics_functions-on-types.md":"D0pqKrGS","ch-generics_golden-rule.md":"Dom36C92","ch-generics_tail-recursion.md":"LajyFN-9","ch-generics_template-dsl-new.md":"BRGf_5TB","ch-generics_template-dsl.md":"kPVbX2z3","ch-generics_test-your-types.md":"CaN1NqIM","ch-generics_type-display.md":"DxdjFduk","ch-inference_all-at-once.md":"BVZ7HAvm","ch-inference_avoid-aliasing.md":"DOqUk1Qd","ch-inference_avoid-inferable.md":"D_9-raWM","ch-inference_context-inference.md":"DSgyVrAZ","ch-inference_evolving-any.md":"3bMMfQeL","ch-inference_functional-libraries.md":"7-KUXtfq","ch-inference_inference-sites.md":"D8IL8vvD","ch-inference_narrowing.md":"Ddb_DPTk","ch-inference_one-var-one-type.md":"CNrTqyYy","ch-inference_use-async-await.md":"z4kCktxH","ch-inference_widening.md":"49jjphV8","ch-intro_any.md":"3O2f-gUR","ch-intro_independent.md":"CUnJzrg_","ch-intro_structural.md":"BMvtIPld","ch-intro_ts-vs-js.md":"B9zmsA34","ch-intro_which-ts.md":"CzfSSKcM","ch-migrate_allowjs.md":"D4_gJxyJ","ch-migrate_convert-up-the-graph.md":"BDsLWrWH","ch-migrate_jsdoc-tscheck.md":"9gnazgll","ch-migrate_start-loose.md":"BhxdRUe3","ch-migrate_write-modern-js.md":"CN3X4_v-","ch-recipes_brands.md":"C4o897iD","ch-recipes_conditional-varargs.md":"DtpgILmG","ch-recipes_exhaustiveness.md":"Di5cKVEs","ch-recipes_iterate-objects.md":"DeIVm3Q4","ch-recipes_optional-never.md":"CWgx2cQa","ch-recipes_values-in-sync.md":"BWlWRACe","ch-types_avoid-object-wrapper-types.md":"HH7dzQbI","ch-types_editor.md":"GuzP-rBD","ch-types_excess-property-checking.md":"DhrQ_GLm","ch-types_index-for-dynamic.md":"KRZXYMSs","ch-types_map-between-types.md":"g8LP3pm5","ch-types_number-index.md":"DHedX37w","ch-types_prefer-declarations-to-assertions.md":"C5YLg3Ey","ch-types_readonly.md":"Chvu4vyV","ch-types_type-entire-functions.md":"a3Ooaj-s","ch-types_type-value-space.md":"CuOg4SD0","ch-types_type-vs-interface.md":"BhLaYCcB","ch-types_types-as-sets.md":"uc3GZnC5","ch-write-run_avoid-non-ecma.md":"EgJw03xs","ch-write-run_model-env.md":"BfMWUYOT","ch-write-run_performance.md":"Cwk5osO2","ch-write-run_runtime-types.md":"DYIbmAqF","ch-write-run_source-maps-debug.md":"C-qAIzwa","ch-write-run_types-or-tests.md":"xySBCB_D","ch-write-run_understand-the-dom.md":"CAjPls7I","index.md":"CCJBNPBL"}
